CHANGELOG.txt
LICENCE.txt
MANIFEST.in
README.txt
setup.py
rosnipe/__init__.py
rosnipe.egg-info/PKG-INFO
rosnipe.egg-info/SOURCES.txt
rosnipe.egg-info/dependency_links.txt
rosnipe.egg-info/requires.txt
rosnipe.egg-info/top_level.txt