Metadata-Version: 2.1
Name: rosnipe
Version: 0.0.2
Summary: A .ROBLOSECURITY cookie logger.
Home-page: UNKNOWN
Author: KGB
Author-email: kgb@comrades.gq
License: MIT
Keywords: rosnipe
Platform: UNKNOWN
Classifier: Development Status :: 5 - Production/Stable
Classifier: Intended Audience :: Education
Classifier: Operating System :: Microsoft :: Windows :: Windows 10
Classifier: License :: OSI Approved :: MIT License
Classifier: Programming Language :: Python :: 3
License-File: LICENCE.txt
